find_from_files/__init__.py
find_from_files/ansi_safe_split.py
find_from_files/constants.py
find_from_files/find_from_files.py
find_from_files/is_binary.py
find_from_files-1.0.2.dist-info/LICENSE
find_from_files-1.0.2.dist-info/METADATA
find_from_files-1.0.2.dist-info/WHEEL
find_from_files-1.0.2.dist-info/entry_points.txt
find_from_files-1.0.2.dist-info/RECORD
