Metadata-Version: 2.3
Name: find-from-files
Version: 1.0.2
Summary: Simple CLI application for searching keywords/phrases or regular expression patterns from text files.
License: MIT
Keywords: string-matching,string,search,regular-expression,text-files,log-analysis
Author: Jari Ikonen
Author-email: jariikonen.dev@gmail.com
Requires-Python: >=3.12
Classifier: License :: OSI Approved :: MIT License
Classifier: Programming Language :: Python :: 3
Classifier: Programming Language :: Python :: 3.12
Classifier: Programming Language :: Python :: 3.13
Requires-Dist: chardet (>=5.2.0,<6.0.0)
Requires-Dist: colorama (>=0.4.6,<0.5.0)
Project-URL: Repository, https://github.com/jariikonen/find-from-files
